pdfformfields/__init__.py
pdfformfields/wrapper.py
pdfformfields/wrapper_runtime_tests.py
pdfformfields-0.0.3.dist-info/LICENSE
pdfformfields-0.0.3.dist-info/METADATA
pdfformfields-0.0.3.dist-info/WHEEL
pdfformfields-0.0.3.dist-info/top_level.txt
pdfformfields-0.0.3.dist-info/RECORD
