Metadata-Version: 2.1
Name: pdfformfields
Version: 0.0.3
Summary: pdfformfields is a Python wrapper around pdftk that fills in pdf forms from a Python dictionary.
Home-page: https://github.com/Balonger/pdfformfields
Author: Nguyen Ba Long
Author-email: Nguyen.Ba.Long13@gmail.com
License: GPLv3+
Platform: UNKNOWN
Classifier: Development Status :: 4 - Beta
Classifier: License :: OSI Approved :: GNU General Public License v3 or later (GPLv3+)
Classifier: Programming Language :: Python
Classifier: Programming Language :: Python :: 3.6
Classifier: Topic :: Software Development :: Libraries
Classifier: Topic :: Software Development :: Libraries :: Python Modules
Classifier: Intended Audience :: Developers
Requires-Python: >=3.7
Requires-Dist: xfdfgen
